omni_cv_rules/__init__.py
omni_cv_rules/coconut/__coconut__.py
omni_cv_rules/coconut/__init__.py
omni_cv_rules/coconut/convert.py
omni_cv_rules/coconut/omni_converter.py
omni_cv_rules/coconut/recursive.py
omni_cv_rules/coconut/to_bytes.py
omni_cv_rules/coconut/torch_rules.py
omni_cv_rules/coconut/visualization.py
omni_cv_rules/coconut/widgets.py
omni_cv_rules/custom_rules.py
omni_cv_rules/image_ops.py
omni_cv_rules/nrm_quiver.py
omni_cv_rules/place_holder/__init__.py
omni_cv_rules/place_holder/torch_proxy.py
omni_cv_rules/py_310/__init__.py
omni_cv_rules/py_38/__init__.py
omni_cv_rules/py_38/torch_rules.py
omni_cv_rules/rulebook.py
omni_cv_rules-0.1.16.dist-info/LICENSE
omni_cv_rules-0.1.16.dist-info/METADATA
omni_cv_rules-0.1.16.dist-info/WHEEL
omni_cv_rules-0.1.16.dist-info/RECORD
