Metadata-Version: 2.1
Name: omni-cv-rules
Version: 0.1.16
Summary: 
License: MIT
Author: proboscis
Author-email: nameissoap@gmail.com
Requires-Python: >=3.7,<4.0
Classifier: License :: OSI Approved :: MIT License
Classifier: Programming Language :: Python :: 3
Classifier: Programming Language :: Python :: 3.7
Classifier: Programming Language :: Python :: 3.8
Classifier: Programming Language :: Python :: 3.9
Classifier: Programming Language :: Python :: 3.10
Classifier: Programming Language :: Python :: 3.11
Requires-Dist: Pillow
Requires-Dist: attrs
Requires-Dist: bqplot
Requires-Dist: frozendict
Requires-Dist: ipywidgets
Requires-Dist: numpy
Requires-Dist: pandas
Requires-Dist: pprintpp
Requires-Dist: py-omni-converter
